func_prototypes/__init__.py
func_prototypes/util.py
func_prototypes-0.5.dist-info/LICENSE
func_prototypes-0.5.dist-info/METADATA
func_prototypes-0.5.dist-info/WHEEL
func_prototypes-0.5.dist-info/top_level.txt
func_prototypes-0.5.dist-info/RECORD
