Metadata-Version: 2.1
Name: func-prototypes
Version: 0.5
Summary: library which helps people constrain python functions by type.
Home-page: https://github.com/andrewguy9/func_prototypes
Author: Andrew Thomson
Author-email: athomsonguy@gmail.com
License: MIT
Platform: UNKNOWN
Classifier: License :: OSI Approved :: MIT License
Classifier: Topic :: Software Development :: Libraries
Classifier: Programming Language :: Python :: 3.7
Classifier: Programming Language :: Python :: 2.7
